part_02/section_08/01_D_flip_flop/adder.sv
    module top(
    input      rst,clk,
    input      din,
    output reg dout
    );
      
    always@(posedge clk)
    begin
     if(rst == 1'b1)
        dout <= 1'b0;
     else 
        dout <= din;
    end  
     
     
    initial begin
    $dumpfile("dump.vcd");
    $dumpvars(1,top);
    end
     
     
    endmodule

part_02/section_08/01_D_flip_flop/dump.vcd
$date
	Thu May 28 19:19:54 2026
$end
$version
	Icarus Verilog
$end
$timescale
	1ps
$end
$scope module top $end
$var wire 1 ! clk $end
$var wire 1 " din $end
$var wire 1 # rst $end
$var reg 1 $ dout $end
$upscope $end
$enddefinitions $end
$comment Show the parameter values. $end
$dumpall
$end
#0
$dumpvars
0$
1#
z"
1!
$end
#10000
0!
#20000
1!
#30000
0!
#40000
1!
#50000
0!
#60000
1!
#70000
0!
#80000
1!
#90000
0!
#100000
1!
0#
0"
#110000
0!
#120000
1"
1!
#130000
0!
#140000
1$
1!
#150000
0!
#160000
0"
1!
#170000
0!
#180000
0$
1!
#190000
0!
#200000
1"
1!
#210000
0!
#220000
1$
1!
#230000
0!
#240000
0"
1!
#250000
0!
#260000
0$
1!
#270000
0!
#280000
1!
#290000
0!
#300000
1!
#310000
0!
#320000
1"
1!
#330000
0!
#340000
1$
1!
