part_02/section_07/01_4-bit-adder/adder.sv
`timescale 1ns/1ps
 
module adder(
input      [3:0] a,b,
output reg [4:0] y
);
 
always@(*)
  begin
    y = a + b;
  end
 
initial begin
$dumpfile("dump.vcd");
$dumpvars(1,adder);
end
 
endmodule

part_02/section_07/01_4-bit-adder/dump.vcd
$date
	Thu May 28 19:12:39 2026
$end
$version
	Icarus Verilog
$end
$timescale
	1ps
$end
$scope module adder $end
$var wire 4 ! a [3:0] $end
$var wire 4 " b [3:0] $end
$var reg 5 # y [4:0] $end
$upscope $end
$enddefinitions $end
$comment Show the parameter values. $end
$dumpall
$end
#0
$dumpvars
b111 #
b111 "
b0 !
$end
#10000
b1011 #
b1011 "
#20000
b11011 #
b1110 "
b1101 !
#30000
b11000 #
b1001 "
b1111 !
#40000
b101 #
b1 "
b100 !
#50000
b10001 #
b1001 "
b1000 !
#60000
b100 "
b1101 !
#70000
b11 #
b1 "
b10 !
#80000
b10000 #
b1011 "
b101 !
#90000
b10001 #
b100 "
b1101 !
