part_02/section_01/01_generation_signals/adder.sv
`timescale 1ns/1ps

module mux(
    input [3:0] addr, din,
    output reg full
    );

    // Dump waveforms for post-simulation debugging.
    initial begin
        full = 1'b0;
        #450;
        full = 1'b1;
    end

    // Dump waveforms for post-simulation debugging.
    initial begin
        $dumpfile("dump.vcd");
        $dumpvars(1,mux);/// all the variables of specified module : mux
        #500;
        $finish;
    end

endmodule

part_02/section_01/01_generation_signals/dump.vcd
$date
	Thu May 28 23:00:14 2026
$end
$version
	Icarus Verilog
$end
$timescale
	1ps
$end
$scope module mux $end
$var wire 4 ! addr [3:0] $end
$var wire 4 " din [3:0] $end
$var reg 1 # full $end
$upscope $end
$enddefinitions $end
#0
$dumpvars
0#
b1010 "
b1101 !
$end
#10000
b101 "
b10 !
#20000
b101 !
#30000
b1100 "
b1001 !
#40000
b11 "
#50000
b1001 "
b11 !
#60000
b1 "
b1101 !
#70000
b101 "
b1010 !
#80000
b100 "
b101 !
#90000
b111 "
b1001 !
#100000
b1100 "
b1000 !
#110000
b1011 "
b0 !
#120000
b101 "
b101 !
#130000
b1 "
b111 !
#140000
b1101 "
b1 !
#150000
b0 "
b100 !
#160000
b11 "
b1100 !
#170000
b1111 "
b1 !
#180000
b1000 "
b11 !
#190000
b0 "
b1101 !
#200000
b1101 "
b1010 !
#210000
b1010 "
#220000
b1111 "
b111 !
#230000
b1101 "
b0 !
#240000
b10 "
b1001 !
#250000
b1000 "
b101 !
#260000
b0 "
b1 !
#270000
b10 "
b1101 !
#280000
b1000 "
b1000 !
#290000
b11 "
b1111 !
#300000
b1111 "
b1100 !
#310000
b111 "
b1 !
#320000
b1110 "
b101 !
#330000
b1000 "
b1010 !
#340000
b1100 "
b1100 !
#350000
b111 "
b10 !
#360000
b1001 "
b1011 !
#370000
b100 "
b1 !
#380000
b1000 !
#390000
b1010 "
b10 !
#400000
b100 "
b1001 !
#410000
b1101 "
b101 !
#420000
b11 "
b1011 !
#430000
b101 "
b1101 !
#440000
b1101 "
b1111 !
#450000
1#
