part_02/section_08/02_memory/adder.sv
    module top(
    input rst,clk,
    input wr,
    input [7:0] din,
    input [3:0] addr,
    output [7:0] dout
    );
     
    reg [7:0] mem [16];
    reg [7:0] temp = 8'h00;
     
    always@(posedge clk)
    begin
        if     (rst == 1'b1)
          begin
          	for (int i =0; i < 16; i++)
               begin
           	   mem[i] <= 0;
               end
            temp      <= 8'h0;
           end
        else if (wr == 1'b1)
          begin
          mem[addr] <= din;
          end
        else
          temp      <= mem[addr];      
    end
     
     
    assign dout = temp;
     
     
     
    initial begin
    $dumpfile("dump.vcd");
    $dumpvars(1,top);
    end
     
     
    endmodule

part_02/section_08/02_memory/dump.vcd
$date
	Thu May 28 19:21:28 2026
$end
$version
	Icarus Verilog
$end
$timescale
	1ps
$end
$scope module top $end
$var wire 4 ! addr [3:0] $end
$var wire 1 " clk $end
$var wire 8 # din [7:0] $end
$var wire 8 $ dout [7:0] $end
$var wire 1 % rst $end
$var wire 1 & wr $end
$var reg 8 ' temp [7:0] $end
$upscope $end
$enddefinitions $end
$comment Show the parameter values. $end
$dumpall
$end
#0
$dumpvars
b0 '
z&
1%
b0 $
bz #
1"
bz !
$end
#10000
0"
#20000
1"
#30000
0"
#40000
1"
#50000
0"
#60000
1"
#70000
0"
#80000
1"
#90000
0"
#100000
1&
b1011 !
b1111001 #
bx $
bx '
1"
0%
#110000
0"
#120000
b1100 !
b1011100 #
1"
#130000
0"
#140000
1"
#150000
0"
#160000
b10 !
b10011011 #
1"
#170000
0"
#180000
1"
#190000
0"
#200000
b111 !
b111100 #
1"
#210000
0"
#220000
1"
#230000
0"
#240000
b11 !
b10001001 #
1"
#250000
0"
#260000
1"
#270000
0"
#280000
b1000 !
b10001110 #
1"
#290000
0"
#300000
1"
#310000
0"
#320000
b0 !
b11110110 #
1"
#330000
0"
#340000
1"
#350000
0"
#360000
b1000 !
b11100110 #
1"
#370000
0"
#380000
1"
#390000
0"
#400000
b110 !
b100011 #
1"
#410000
0"
#420000
1"
#430000
0"
#440000
b1011 !
b1100111 #
1"
#450000
0"
#460000
1"
#470000
0"
#480000
b1110 !
b11010111 #
1"
#490000
0"
#500000
1"
#510000
0"
#520000
b100 !
b11110001 #
1"
#530000
0"
#540000
1"
#550000
0"
#560000
b1001 !
b11000010 #
1"
#570000
0"
#580000
1"
#590000
0"
#600000
b1000 !
b10001110 #
1"
#610000
0"
#620000
1"
#630000
0"
#640000
b10011011 #
1"
#650000
0"
#660000
1"
#670000
0"
#680000
b0 !
0&
1"
#690000
0"
#700000
b11110110 $
b11110110 '
1"
#710000
0"
#720000
b1000 !
1"
#730000
0"
#740000
b10011011 $
b10011011 '
1"
#750000
0"
#760000
b110 !
1"
#770000
0"
#780000
b100011 $
b100011 '
1"
#790000
0"
#800000
b1011 !
1"
#810000
0"
#820000
b1100111 $
b1100111 '
1"
#830000
0"
#840000
b1000 !
1"
#850000
0"
#860000
b10011011 $
b10011011 '
1"
#870000
0"
#880000
b1010 !
1"
#890000
0"
#900000
b0 $
b0 '
1"
#910000
0"
#920000
b11 !
1"
#930000
0"
#940000
b10001001 $
b10001001 '
1"
#950000
0"
#960000
b1 !
1"
#970000
0"
#980000
b0 $
b0 '
1"
#990000
0"
#1000000
b1001 !
1"
#1010000
0"
#1020000
b11000010 $
b11000010 '
1"
#1030000
0"
#1040000
b1100 !
1"
#1050000
0"
#1060000
b1011100 $
b1011100 '
1"
#1070000
0"
#1080000
1"
#1090000
0"
#1100000
1"
#1110000
0"
#1120000
b1110 !
1"
#1130000
0"
#1140000
b11010111 $
b11010111 '
1"
#1150000
0"
#1160000
b100 !
1"
#1170000
0"
#1180000
b11110001 $
b11110001 '
1"
#1190000
0"
#1200000
b10 !
1"
#1210000
0"
#1220000
b10011011 $
b10011011 '
1"
#1230000
0"
#1240000
b1100 !
1"
#1250000
0"
#1260000
b1011100 $
b1011100 '
1"
