part_02/section_05/02_priority_encoder/adder.sv
    module pri_enc(
      input en,
      input [7:0]i,
      output reg [2:0]y
      );
      
      always@(*)
      begin
        if(en==1)
          begin
            if(i[7]==1) y=3'b111;
            else if(i[6]==1) y=3'b110;
            else if(i[5]==1) y=3'b101;
            else if(i[4]==1) y=3'b100;
            else if(i[3]==1) y=3'b011;
            else if(i[2]==1) y=3'b010;
            else if(i[1]==1) y=3'b001;
            else if(i[0]==1) y=3'b000;
            else
            y=3'b000;
          end
        else y=3'b000;
      end
      
      
    initial begin
    $dumpfile("dump.vcd");
    $dumpvars(1,pri_enc);
    end
     
     
     
    endmodule

part_02/section_05/02_priority_encoder/dump.vcd
$date
	Thu May 28 15:09:29 2026
$end
$version
	Icarus Verilog
$end
$timescale
	1ps
$end
$scope module pri_enc $end
$var wire 1 ! en $end
$var wire 8 " i [7:0] $end
$var reg 3 # y [2:0] $end
$upscope $end
$enddefinitions $end
$comment Show the parameter values. $end
$dumpall
$end
#0
$dumpvars
b101 #
b101110 "
1!
$end
#20000
b110 #
b1110100 "
#40000
b11 #
b1011 "
#60000
b110 #
b1011100 "
#80000
b100 #
b11111 "
#100000
b110 #
b1010011 "
#120000
b1010110 "
#140000
b1101100 "
#160000
b101 #
b100101 "
#180000
b111 #
b11101110 "
#200000
b10000100 "
#220000
b110 #
b1011111 "
#240000
b1010111 "
#260000
b111 #
b11100101 "
#280000
b101 #
b111100 "
#300000
b110 #
b1101100 "
#320000
b111 #
b11101000 "
#340000
b10110011 "
#360000
b10011010 "
#380000
b110 #
b1000110 "
#400000
b11 #
b1011 "
#420000
b111 #
b11011010 "
#440000
b110 #
b1001000 "
#460000
b101 #
b111010 "
#480000
b111 #
b11100111 "
#500000
b11000000 "
#520000
b101 #
b100111 "
#540000
b101010 "
#560000
b110 #
b1000011 "
#580000
b1001000 "
