part_02/section_07/02_8_mux/adder.sv
    module mux(
      input [7:0] din,
      input [2:0] sel,
      output reg  dout
      );
      
      always@(*)
      begin
        case(sel)
        3'b000:dout = din[0];
        3'b001:dout = din[1];
        3'b010:dout = din[2];
        3'b011:dout = din[3];
        3'b100:dout = din[4];
        3'b101:dout = din[5];
        3'b110:dout = din[6];
        3'b111:dout = din[7];
        default: dout = 1'b0;
        endcase
      end
      
      
    initial begin
    $dumpfile("dump.vcd");
    $dumpvars(1,mux);
    end
     
     
     
    endmodule

part_02/section_07/02_8_mux/dump.vcd
$date
	Thu May 28 19:14:21 2026
$end
$version
	Icarus Verilog
$end
$timescale
	1ps
$end
$scope module mux $end
$var wire 8 ! din [7:0] $end
$var wire 3 " sel [2:0] $end
$var reg 1 # dout $end
$upscope $end
$enddefinitions $end
$comment Show the parameter values. $end
$dumpall
$end
#0
$dumpvars
0#
b1 "
b1101001 !
$end
#20000
1#
b111 "
b10010001 !
#40000
0#
b101 "
b1011101 !
#60000
1#
b10 "
b1110101 !
#80000
0#
b110 "
b10000000 !
#100000
1#
b11 "
b1111110 !
#120000
b1 "
b10111110 !
#140000
b0 "
b1110101 !
#160000
b100 "
b1111000 !
#180000
0#
b1001000 !
#200000
b111 "
b1011101 !
#220000
b100 "
b11000001 !
#240000
b0 "
b11101000 !
#260000
1#
b111 "
b11111111 !
#280000
0#
b1 "
b11110101 !
#300000
1#
b101 "
b10111110 !
#320000
b110 "
b11111111 !
#340000
0#
b10 "
b11001 !
#360000
1#
b110 "
b11101011 !
#380000
b101 "
b1111111 !
#400000
b11 "
b1001001 !
#420000
0#
b10 "
b11111010 !
#440000
1#
b0 "
b11 !
#460000
b10 "
b10100111 !
#480000
b111 "
b10000010 !
#500000
b11 "
b11111111 !
#520000
b101 "
b110000 !
#540000
b0 "
b1101 !
#560000
0#
b11 "
b10110010 !
#580000
1#
b1 "
b11001010 !
