part_02/section_05/03_integer/adder.sv
module pri_enc(
    input en,
    input [7:0]i,
    output reg [2:0]y
    );

    always @(*)
    begin
        if (en==1)
        begin
            if (i[7]==1) y=3'b111;
            else if (i[6]==1) y=3'b110;
            else if (i[5]==1) y=3'b101;
            else if (i[4]==1) y=3'b100;
            else if (i[3]==1) y=3'b011;
            else if (i[2]==1) y=3'b010;
            else if (i[1]==1) y=3'b001;
            else if (i[0]==1) y=3'b000;
            else
                y=3'b000;
        end
        else y=3'b000;
    end

    // Dump waveforms for post-simulation debugging.
    initial begin
        $dumpfile("dump.vcd");
        $dumpvars(1,pri_enc);
    end

endmodule

part_02/section_05/03_integer/dump.vcd
$date
	Thu May 28 15:07:07 2026
$end
$version
	Icarus Verilog
$end
$timescale
	1ps
$end
$scope module pri_enc $end
$var wire 1 ! en $end
$var wire 8 " i [7:0] $end
$var reg 3 # y [2:0] $end
$upscope $end
$enddefinitions $end
$comment Show the parameter values. $end
$dumpall
$end
#0
$dumpvars
b111 #
b11000010 "
1!
$end
#20000
b110 #
b1110101 "
#40000
b111 #
b11010101 "
#60000
b10011101 "
#80000
b10011000 "
#100000
b11110101 "
#120000
b10011010 "
#140000
b11010011 "
#160000
b101 #
b111011 "
#180000
b11 #
b1110 "
#200000
b110 #
b1000000 "
#220000
b100 #
b10011 "
#240000
b11100 "
#260000
b111 #
b10101011 "
#280000
b110 #
b1111011 "
#300000
b111 #
b10000111 "
#320000
b110 #
b1011100 "
#340000
b111 #
b10000100 "
#360000
b11000000 "
#380000
b100 #
b11001 "
#400000
b110 #
b1011110 "
#420000
b10 #
b111 "
#440000
b111 #
b10100101 "
#460000
b101 #
b101010 "
#480000
b110 #
b1100001 "
#500000
b111 #
b11001001 "
#520000
b11101011 "
#540000
b110 #
b1101101 "
#560000
b1100011 "
#580000
b111 #
b11010000 "
